LICENSE
MANIFEST.in
README.md
requirements.txt
setup.cfg
setup.py
cartomap/__init__.py
cartomap/cartomap.py
cartomap/common.py
cartomap.egg-info/PKG-INFO
cartomap.egg-info/SOURCES.txt
cartomap.egg-info/dependency_links.txt
cartomap.egg-info/not-zip-safe
cartomap.egg-info/top_level.txt